{
  "eatingLocation" : "Eating location",
  "dineIn":"Dine in",
  "takeOut": "Take out",
  "createYourMenu": "Create your menu",
  "startOver" : "Start Over",
  "modifyOrPay" : "Modify or pay",
  "burgers" : "Burgers",
  "drinks": "Drinks",
  "sides" : "Sides",
  "personalizedBurger" : "Create your own personalized burger!",
  "total" : "Total:",
  "customBurger" : "Custom Burger",
  "mainPage" : "Main page",
  "sum" :"Sum",
  "ordersSummary" : "Order summary",
  "pay" : "Pay",
  "addAnItem" : "Add an item",
  "orderState" : "Orders State",
  "notStarted" : "Not started",
  "started" : "Started",
  "finished" : "Finished",
  "language" : "Svenska"
}
